{
  "tag": "2020-08-30_133347",
  "event": {
    "event_type": "scroll",
    "x": null,
    "y": null,
    "view": {
      "package": "org.wikipedia.dev",
      "visible": true,
      "checkable": false,
      "child_count": 1,
      "editable": false,
      "clickable": false,
      "is_password": false,
      "focusable": true,
      "enabled": true,
      "content_description": null,
      "children": [
        14
      ],
      "focused": false,
      "bounds": [
        [
          0,
          258
        ],
        [
          1080,
          1982
        ]
      ],
      "resource_id": null,
      "checked": false,
      "text": null,
      "class": "androidx.recyclerview.widget.RecyclerView",
      "scrollable": true,
      "selected": false,
      "long_clickable": false,
      "parent": 12,
      "temp_id": 13,
      "size": "1080*1724",
      "signature": "[class]androidx.recyclerview.widget.RecyclerView[resource_id]None[text]None[enabled,,]",
      "view_str": "cc468e40bf7f09908af9102966982d74",
      "content_free_signature": "[class]androidx.recyclerview.widget.RecyclerView[resource_id]None"
    },
    "direction": "DOWN"
  },
  "start_state": "e175e650bc90771abaa782e31e6cd7a5",
  "stop_state": "e175e650bc90771abaa782e31e6cd7a5",
  "event_str": "ScrollEvent(state=e175e650bc90771abaa782e31e6cd7a5, view=cc468e40bf7f09908af9102966982d74, direction=DOWN)"
}